lda/__init__.py
lda/_lda.c
lda/_lda.cp37-win32.pyd
lda/_lda.pyx
lda/_setup_hooks.py
lda/datasets.py
lda/gamma.c
lda/gamma.h
lda/lda.py
lda/utils.py
lda/tests/__init__.py
lda/tests/reuters.ldac
lda/tests/reuters.titles
lda/tests/reuters.tokens
lda/tests/test_datasets.py
lda/tests/test_lda.py
lda/tests/test_lda_reuters.py
lda/tests/test_lda_sparse.py
lda/tests/test_lda_transform.py
lda/tests/test_utils.py
ldafork-1.2.0.dist-info/AUTHORS
ldafork-1.2.0.dist-info/LICENSE
ldafork-1.2.0.dist-info/METADATA
ldafork-1.2.0.dist-info/WHEEL
ldafork-1.2.0.dist-info/pbr.json
ldafork-1.2.0.dist-info/top_level.txt
ldafork-1.2.0.dist-info/RECORD
